{"items":{"serializeList":[{"name":"hay","nr":3242805635.0},{"name":"wood","nr":5273468179.0},{"name":"carrot","nr":1108589261.0},{"name":"pumpkin","nr":429196922.0},{"name":"cactus","nr":82544497.0},{"name":"bone","nr":11988940.0},{"name":"weird_substance","nr":955758294.0},{"name":"gold","nr":4362024.0},{"name":"water","nr":2991009.0},{"name":"fertilizer","nr":71032.0},{"name":"power","nr":506908.6663333375}]},"dockedFiles":[{"key":"2. LIBRARIES","value":"Bone"},{"key":"3. TEST","value":"Logger"},{"key":"4. FUN","value":"f0"},{"key":"Bone","value":"Gold"},{"key":"Bulk","value":"Math"},{"key":"Cactus","value":"Power"},{"key":"Carrot","value":"Wood"},{"key":"Clear","value":"3. TEST"},{"key":"Companion","value":"Planter"},{"key":"Constants","value":"Path"},{"key":"f0","value":"Clear"},{"key":"Gold","value":"Cactus"},{"key":"Hay","value":"1. PRODUCTION"},{"key":"LeaderboardFR2","value":"LeaderboardFullReset"},{"key":"LeaderboardFullReset","value":"Leaderboard"},{"key":"List","value":"Random"},{"key":"Logger","value":"Bulk"},{"key":"Math","value":"Thread"},{"key":"Move","value":"Utils"},{"key":"Path","value":"Move"},{"key":"Planter","value":"List"},{"key":"Plotter","value":"4. FUN"},{"key":"Power","value":"Pumpkin"},{"key":"Pumpkin","value":"Carrot"},{"key":"Random","value":"Constants"},{"key":"Thread","value":"Companion"},{"key":"Utils","value":"2. LIBRARIES"},{"key":"Wood","value":"Hay"}],"minimizedFiles":["Bone","Bulk","Cactus","Carrot","Clear","Companion","Constants","f0","Gold","Hay","Leaderboard","LeaderboardFullReset","List","Logger","Math","Move","Path","Planter","Plotter","Power","Pumpkin","Random","Thread","Utils","Wood"],"openFilePositions":[{"key":"1. PRODUCTION","value":{"x":4863.794921875,"y":1902.4151611328125}},{"key":"2. LIBRARIES","value":{"x":1482.634765625,"y":269.14404296875}},{"key":"3. TEST","value":{"x":1482.634765625,"y":269.14404296875}},{"key":"4. FUN","value":{"x":1482.634765625,"y":269.14404296875}},{"key":"Bone","value":{"x":1482.634765625,"y":269.14404296875}},{"key":"Bulk","value":{"x":1482.634765625,"y":269.14404296875}},{"key":"Cactus","value":{"x":1482.634765625,"y":269.14404296875}},{"key":"Carrot","value":{"x":1482.634765625,"y":269.14404296875}},{"key":"Clear","value":{"x":1482.634765625,"y":269.14404296875}},{"key":"Companion","value":{"x":1482.634765625,"y":269.14404296875}},{"key":"Constants","value":{"x":1482.634765625,"y":269.14404296875}},{"key":"f0","value":{"x":1482.634765625,"y":269.14404296875}},{"key":"Gold","value":{"x":1482.634765625,"y":269.14404296875}},{"key":"Hay","value":{"x":1482.634765625,"y":269.14404296875}},{"key":"Leaderboard","value":{"x":-1384.59765625,"y":1007.0697021484375}},{"key":"LeaderboardFR2","value":{"x":1482.634765625,"y":269.14404296875}},{"key":"LeaderboardFullReset","value":{"x":1482.634765625,"y":269.14404296875}},{"key":"List","value":{"x":1482.634765625,"y":269.14404296875}},{"key":"Logger","value":{"x":1482.634765625,"y":269.14404296875}},{"key":"Math","value":{"x":1482.634765625,"y":269.14404296875}},{"key":"Move","value":{"x":1482.634765625,"y":269.14404296875}},{"key":"Path","value":{"x":1482.634765625,"y":269.14404296875}},{"key":"Planter","value":{"x":1482.634765625,"y":269.14404296875}},{"key":"Plotter","value":{"x":1482.634765625,"y":269.14404296875}},{"key":"Power","value":{"x":1482.634765625,"y":269.14404296875}},{"key":"Pumpkin","value":{"x":1482.634765625,"y":269.14404296875}},{"key":"Random","value":{"x":1482.634765625,"y":269.14404296875}},{"key":"Thread","value":{"x":1482.634765625,"y":269.14404296875}},{"key":"Utils","value":{"x":1482.634765625,"y":269.14404296875}},{"key":"Wood","value":{"x":1482.634765625,"y":269.14404296875}},{"key":"docs0","value":{"x":-2398.525390625,"y":736.2657470703125}}],"openFileScrollPositions":[{"key":"1. PRODUCTION","value":0.0},{"key":"2. LIBRARIES","value":0.0},{"key":"3. TEST","value":0.0},{"key":"4. FUN","value":0.0},{"key":"Bone","value":858.874755859375},{"key":"Bulk","value":427.28863525390627},{"key":"Cactus","value":-0.0008544921875},{"key":"Carrot","value":-0.0010986328125},{"key":"Clear","value":0.001495361328125},{"key":"Companion","value":311.0968322753906},{"key":"Constants","value":199.9986572265625},{"key":"f0","value":149.999267578125},{"key":"Gold","value":1889.9920654296875},{"key":"Hay","value":-0.00030517578125},{"key":"Leaderboard","value":0.0},{"key":"LeaderboardFR2","value":1749.9990234375},{"key":"LeaderboardFullReset","value":0.0},{"key":"List","value":99.9996337890625},{"key":"Logger","value":292.239990234375},{"key":"Math","value":0.00115966796875},{"key":"Move","value":-0.00152587890625},{"key":"Path","value":2359.858154296875},{"key":"Planter","value":1326.874267578125},{"key":"Plotter","value":586.7304077148438},{"key":"Power","value":-0.00067138671875},{"key":"Pumpkin","value":-0.0006103515625},{"key":"Random","value":0.0},{"key":"Thread","value":76.39620971679688},{"key":"Utils","value":0.0},{"key":"Wood","value":152.209716796875}],"openFileSizes":[{"key":"1. PRODUCTION","value":{"x":0.0,"y":0.0}},{"key":"2. LIBRARIES","value":{"x":0.0,"y":0.0}},{"key":"3. TEST","value":{"x":0.0,"y":0.0}},{"key":"4. FUN","value":{"x":0.0,"y":0.0}},{"key":"Bone","value":{"x":2136.046142578125,"y":788.9252319335938}},{"key":"Bulk","value":{"x":1062.7879638671875,"y":836.991943359375}},{"key":"Cactus","value":{"x":1080.6876220703125,"y":931.3966064453125}},{"key":"Carrot","value":{"x":896.1177978515625,"y":921.1686401367188}},{"key":"Clear","value":{"x":0.0,"y":0.0}},{"key":"Companion","value":{"x":1054.354248046875,"y":1136.1500244140625}},{"key":"Constants","value":{"x":698.7421264648438,"y":600.0}},{"key":"f0","value":{"x":1282.9892578125,"y":1154.048583984375}},{"key":"Gold","value":{"x":1209.4249267578125,"y":776.4343872070313}},{"key":"Hay","value":{"x":694.6998291015625,"y":650.31591796875}},{"key":"Leaderboard","value":{"x":934.7759399414063,"y":391.8359680175781}},{"key":"LeaderboardFR2","value":{"x":1552.5025634765625,"y":1301.7117919921875}},{"key":"LeaderboardFullReset","value":{"x":1272.7099609375,"y":3125.042236328125}},{"key":"List","value":{"x":955.1353149414063,"y":814.6270751953125}},{"key":"Logger","value":{"x":0.0,"y":0.0}},{"key":"Math","value":{"x":1059.928466796875,"y":640.5806274414063}},{"key":"Move","value":{"x":818.6214599609375,"y":980.1552734375}},{"key":"Path","value":{"x":0.0,"y":1182.734375}},{"key":"Planter","value":{"x":0.0,"y":910.28662109375}},{"key":"Plotter","value":{"x":1145.986328125,"y":763.3495483398438}},{"key":"Power","value":{"x":1194.9217529296875,"y":1035.24267578125}},{"key":"Pumpkin","value":{"x":1092.948974609375,"y":977.9600830078125}},{"key":"Random","value":{"x":743.26171875,"y":321.6744689941406}},{"key":"Thread","value":{"x":1339.597412109375,"y":881.51806640625}},{"key":"Utils","value":{"x":720.3375244140625,"y":222.44830322265626}},{"key":"Wood","value":{"x":1101.037353515625,"y":625.560302734375}},{"key":"docs0","value":{"x":878.038330078125,"y":700.0}}],"openDocPages":[{"key":"docs0","value":"docs/output.md"}],"unlocks":["grass_10","soil","harvest","pass","do_a_flip","pet_the_piggy","grassland","hay","straw_hat","while","true","false","break","continue","loops","speed_5","can_harvest","if","else","elif","expand_9","move","north","south","east","west","for","range","get_world_size","wood","bush","entities","clear","plant","carrots_10","carrot","till","can_trade","trade","items","carrot_seed","and","or","not","operators","print","quick_print","unlocks","str","debug","get_entity_type","get_ground_type","grounds","get_pos_x","get_pos_y","none","num_items","num_unlocked","senses","variables","change_hat","gray_hat","purple_hat","green_hat","brown_hat","hats","trees_10","tree","tree_hat","watering_9","water","use_item","get_water","functions","def","return","global","traffic_cone","from","import","carrot_hat","sunflower_seed","sunflower","power","get_active_power","measure","sunflowers","fertilizer_4","weird_substance","pumpkins_10","pumpkin","pumpkin_seed","dead_pumpkin","append","remove","pop","insert","len","list","lists","min","max","abs","random","utilities","get_time","get_tick_count","timing","swap","cactus_seed","cactus_6","get_companion","polyculture_5","dicts","sets","add","dict","set","dictionaries","get_cost","costs","unlock","auto_unlock","sunflower_hat","cactus_hat","dinosaurs_6","dinosaur","egg","bone","dinosaur_hat","apple","can_move","wizard_hat","mazes_6","hedge","treasure","gold","gold_hat","set_execution_speed","set_world_size","debug_2","simulate","simulation","megafarm_5","get_drone_id","num_drones","max_drones","wait_for","spawn_drone","has_finished","golden_cactus_hat","leaderboard_run","leaderboards","leaderboard","traffic_cone_stack","pumpkin_hat","golden_sunflower_hat","the_farmers_remains","golden_tree_hat","golden_carrot_hat","golden_gold_hat","top_hat"],"version":3}